{
    "status": "Success",
    "data": [
        {
            "id": "1",
            "name": "\u0627\u0644\u0634\u0645\u0627\u0644\u064a\u0629",
            "parent": "0",
            "parent_name": null
        },
        {
            "id": "2",
            "name": "\u0627\u0644\u0627\u0633\u0643\u0646\u062f\u0631\u064a\u0629",
            "parent": "1",
            "parent_name": "\u0627\u0644\u0634\u0645\u0627\u0644\u064a\u0629"
        },
        {
            "id": "3",
            "name": "\u0645\u0637\u0631\u0648\u062d",
            "parent": "1",
            "parent_name": "\u0627\u0644\u0634\u0645\u0627\u0644\u064a\u0629"
        },
        {
            "id": "6",
            "name": "\u0627\u0644\u062c\u0646\u0648\u0628\u064a\u0629",
            "parent": "0",
            "parent_name": null
        },
        {
            "id": "7",
            "name": "\u0627\u0633\u0648\u0627\u0646",
            "parent": "6",
            "parent_name": "\u0627\u0644\u062c\u0646\u0648\u0628\u064a\u0629"
        },
        {
            "id": "8",
            "name": "\u0627\u0644\u063a\u0631\u0628\u064a\u0629",
            "parent": "0",
            "parent_name": null
        },
        {
            "id": "17",
            "name": "\u0627\u0644\u0645\u0646\u062a\u0632\u0647",
            "parent": "2",
            "parent_name": "\u0627\u0644\u0627\u0633\u0643\u0646\u062f\u0631\u064a\u0629"
        },
        {
            "id": "24",
            "name": "aaa",
            "parent": "34",
            "parent_name": "aa"
        },
        {
            "id": "25",
            "name": "ccc",
            "parent": "0",
            "parent_name": null
        },
        {
            "id": "27",
            "name": "asdasd",
            "parent": "0",
            "parent_name": null
        },
        {
            "id": "28",
            "name": "uyyuuy",
            "parent": "0",
            "parent_name": null
        },
        {
            "id": "29",
            "name": "ooo",
            "parent": "28",
            "parent_name": "uyyuuy"
        },
        {
            "id": "30",
            "name": "yyy",
            "parent": "29",
            "parent_name": "ooo"
        },
        {
            "id": "31",
            "name": "ppp",
            "parent": "0",
            "parent_name": null
        },
        {
            "id": "32",
            "name": "lll",
            "parent": "31",
            "parent_name": "ppp"
        },
        {
            "id": "33",
            "name": "a",
            "parent": "0",
            "parent_name": null
        },
        {
            "id": "34",
            "name": "aa",
            "parent": "33",
            "parent_name": "a"
        },
        {
            "id": "35",
            "name": "aaaa",
            "parent": "0",
            "parent_name": null
        },
        {
            "id": "36",
            "name": "aaaaa",
            "parent": "0",
            "parent_name": null
        },
        {
            "id": "37",
            "name": "aaaaaa",
            "parent": "0",
            "parent_name": null
        },
        {
            "id": "38",
            "name": "aaaaaaaaa",
            "parent": "0",
            "parent_name": null
        },
        {
            "id": "39",
            "name": "aaaaaaaaaa",
            "parent": "0",
            "parent_name": null
        },
        {
            "id": "40",
            "name": "aaaaaaa",
            "parent": "0",
            "parent_name": null
        },
        {
            "id": "41",
            "name": "saa",
            "parent": "0",
            "parent_name": null
        }
    ]
}